{
  "ticker": "ABI-BE",
  "stage": "Deep Dive",
  "generated": "2026-06-28",
  "source_md": "ABI-BE-Triaging-A-and-J-Memo-2026-06-26.md",
  "ratings": {
    "MR1": {
      "grade": "B",
      "label": "Change thesis"
    },
    "MR2": {
      "grade": "A",
      "label": "Business quality"
    },
    "MR3": {
      "grade": "B",
      "label": "Operator quality"
    },
    "MR4": {
      "grade": "A",
      "label": "Setup quality"
    },
    "MR5": {
      "grade": "C",
      "label": "Risk profile"
    },
    "MR6": {
      "grade": "B",
      "label": "Thematic fit"
    },
    "C.1": {
      "grade": "B",
      "label": "C.1 -- Pillar I: Case change elements"
    },
    "C.2": {
      "grade": "B",
      "label": "C.2 -- Pillar II: Case building blocks"
    },
    "Group 1": {
      "grade": "A",
      "label": "Group 1 -- Case momentum"
    },
    "Group 2": {
      "grade": "B",
      "label": "Group 2 -- Case simplicity"
    },
    "Group 3": {
      "grade": "B",
      "label": "Group 3 -- Core philosophy"
    },
    "Group 4": {
      "grade": "C",
      "label": "Group 4 -- Case riskiness"
    }
  }
}