{
  "ticker": "1U1-DE",
  "stage": "Triaging",
  "generated": "2026-07-15",
  "source_md": "aj-memo-triaging-2026-06-13.md",
  "ratings": {
    "MR1": {
      "grade": "B",
      "label": "MR1 -- Technical momentum"
    },
    "MR2": {
      "grade": "C",
      "label": "MR2 -- Sell-side earnings momentum"
    },
    "MR3": {
      "grade": "C",
      "label": "MR3 -- Thematic fit"
    },
    "MR4": {
      "grade": "B",
      "label": "MR4 -- Pillar I: Case change elements"
    },
    "MR5": {
      "grade": "D",
      "label": "MR5 -- Pillar II: Case building blocks"
    },
    "C.1": {
      "grade": "B",
      "label": "C.1 -- Pillar I: Case change elements"
    },
    "C.2": {
      "grade": "D",
      "label": "C.2 -- Pillar II: Case building blocks"
    },
    "Group 1": {
      "grade": "C",
      "label": "Group 1 -- Case momentum"
    },
    "Group 2": {
      "grade": "D",
      "label": "Group 2 -- Case simplicity"
    },
    "Group 3": {
      "grade": "D",
      "label": "Group 3 -- Core philosophy"
    },
    "Group 4": {
      "grade": "F",
      "label": "Group 4 -- Case riskiness"
    }
  }
}